{
  "id": "0d6b5003",
  "title": "Polymarket research: Wild vs. Golden Knights",
  "assigned_to": "natalia",
  "task_type": "research",
  "params": {
    "query": "Wild vs. Golden Knights",
    "count": 5,
    "context": "polymarket_prediction",
    "requester": "polybot"
  },
  "priority": 3,
  "status": "completed",
  "created_by": "polybot",
  "created_at": "2026-03-07T06:20:34.371184+00:00",
  "updated_at": "2026-03-07T06:21:15.025877+00:00",
  "claimed_at": "2026-03-07T06:21:13.454420+00:00",
  "completed_at": "2026-03-07T06:21:15.025861+00:00",
  "retries": 0,
  "result": {
    "summary": "Research: Wild vs. Golden Knights\n\nWeb Results (0):\n  No web results found.",
    "web_results": [],
    "news_results": [],
    "query": "Wild vs. Golden Knights",
    "sources_count": 0
  },
  "error": null
}