{
  "id": "1f9d1d01",
  "title": "Polymarket research: Spread: Pistons (-5.5)",
  "assigned_to": "natalia",
  "task_type": "research",
  "params": {
    "query": "Spread: Pistons (-5.5)",
    "count": 5,
    "context": "polymarket_prediction",
    "requester": "polybot"
  },
  "priority": 3,
  "status": "completed",
  "created_by": "polybot",
  "created_at": "2026-03-02T01:03:30.938575+00:00",
  "updated_at": "2026-03-02T01:03:46.419118+00:00",
  "claimed_at": "2026-03-02T01:03:44.815972+00:00",
  "completed_at": "2026-03-02T01:03:46.419105+00:00",
  "retries": 0,
  "result": {
    "summary": "Research: Spread: Pistons (-5.5)\n\nWeb Results (0):\n  No web results found.",
    "web_results": [],
    "news_results": [],
    "query": "Spread: Pistons (-5.5)",
    "sources_count": 0
  },
  "error": null
}