{
  "id": "2d1714fd",
  "title": "Polymarket research: Will the US next strike Iran on February 27, 2026 (ET)?",
  "assigned_to": "natalia",
  "task_type": "research",
  "params": {
    "query": "Will the US next strike Iran on February 27, 2026 (ET)?",
    "count": 5,
    "context": "polymarket_prediction",
    "requester": "polybot"
  },
  "priority": 3,
  "status": "completed",
  "created_by": "polybot",
  "created_at": "2026-02-27T04:41:38.831455+00:00",
  "updated_at": "2026-02-27T04:41:46.638230+00:00",
  "claimed_at": "2026-02-27T04:41:45.003793+00:00",
  "completed_at": "2026-02-27T04:41:46.638212+00:00",
  "retries": 0,
  "result": {
    "summary": "Research: Will the US next strike Iran on February 27, 2026 (ET)?\n\nWeb Results (0):\n  No web results found.",
    "web_results": [],
    "news_results": [],
    "query": "Will the US next strike Iran on February 27, 2026 (ET)?",
    "sources_count": 0
  },
  "error": null
}