{
  "id": "2e742917",
  "title": "Polymarket research: Will FC Midtjylland vs. Nottingham Forest FC end in a draw?",
  "assigned_to": "natalia",
  "task_type": "research",
  "params": {
    "query": "Will FC Midtjylland vs. Nottingham Forest FC end in a draw?",
    "count": 5,
    "context": "polymarket_prediction",
    "requester": "polybot"
  },
  "priority": 3,
  "status": "completed",
  "created_by": "polybot",
  "created_at": "2026-03-19T18:09:24.334595+00:00",
  "updated_at": "2026-03-19T18:10:05.529944+00:00",
  "claimed_at": "2026-03-19T18:10:03.696694+00:00",
  "completed_at": "2026-03-19T18:10:05.529925+00:00",
  "retries": 0,
  "result": {
    "summary": "Research: Will FC Midtjylland vs. Nottingham Forest FC end in a draw?\n\nWeb Results (0):\n  No web results found.",
    "web_results": [],
    "news_results": [],
    "query": "Will FC Midtjylland vs. Nottingham Forest FC end in a draw?",
    "sources_count": 0
  },
  "error": null
}