{
  "id": "4098487f",
  "title": "Polymarket research: Lakers vs. Nuggets: O/U 239.5",
  "assigned_to": "natalia",
  "task_type": "research",
  "params": {
    "query": "Lakers vs. Nuggets: O/U 239.5",
    "count": 5,
    "context": "polymarket_prediction",
    "requester": "polybot"
  },
  "priority": 3,
  "status": "completed",
  "created_by": "polybot",
  "created_at": "2026-03-06T03:58:06.693312+00:00",
  "updated_at": "2026-03-06T03:58:22.014938+00:00",
  "claimed_at": "2026-03-06T03:58:20.458683+00:00",
  "completed_at": "2026-03-06T03:58:22.014925+00:00",
  "retries": 0,
  "result": {
    "summary": "Research: Lakers vs. Nuggets: O/U 239.5\n\nWeb Results (0):\n  No web results found.",
    "web_results": [],
    "news_results": [],
    "query": "Lakers vs. Nuggets: O/U 239.5",
    "sources_count": 0
  },
  "error": null
}