{
  "id": "422b2527",
  "title": "Polymarket research: Will Joe Kent win the 2028 Republican presidential nomination?",
  "assigned_to": "natalia",
  "task_type": "research",
  "params": {
    "query": "Will Joe Kent win the 2028 Republican presidential nomination?",
    "count": 5,
    "context": "polymarket_prediction",
    "requester": "polybot"
  },
  "priority": 3,
  "status": "completed",
  "created_by": "polybot",
  "created_at": "2026-03-19T13:31:01.722819+00:00",
  "updated_at": "2026-03-19T13:31:39.762903+00:00",
  "claimed_at": "2026-03-19T13:31:37.991742+00:00",
  "completed_at": "2026-03-19T13:31:39.762889+00:00",
  "retries": 0,
  "result": {
    "summary": "Research: Will Joe Kent win the 2028 Republican presidential nomination?\n\nWeb Results (0):\n  No web results found.",
    "web_results": [],
    "news_results": [],
    "query": "Will Joe Kent win the 2028 Republican presidential nomination?",
    "sources_count": 0
  },
  "error": null
}