{
  "id": "47dd8f0a",
  "title": "Polymarket research: Paradex FDV above $300M one day after launch?",
  "assigned_to": "natalia",
  "task_type": "research",
  "params": {
    "query": "Paradex FDV above $300M one day after launch?",
    "count": 5,
    "context": "polymarket_prediction",
    "requester": "polybot"
  },
  "priority": 3,
  "status": "completed",
  "created_by": "polybot",
  "created_at": "2026-03-06T01:37:19.159888+00:00",
  "updated_at": "2026-03-06T01:38:42.648123+00:00",
  "claimed_at": "2026-03-06T01:38:40.993756+00:00",
  "completed_at": "2026-03-06T01:38:42.648106+00:00",
  "retries": 0,
  "result": {
    "summary": "Research: Paradex FDV above $300M one day after launch?\n\nWeb Results (0):\n  No web results found.",
    "web_results": [],
    "news_results": [],
    "query": "Paradex FDV above $300M one day after launch?",
    "sources_count": 0
  },
  "error": null
}