{
  "id": "5fb9d9b5",
  "title": "Polymarket research: Spurs vs. 76ers",
  "assigned_to": "natalia",
  "task_type": "research",
  "params": {
    "query": "Spurs vs. 76ers",
    "count": 5,
    "context": "polymarket_prediction",
    "requester": "polybot"
  },
  "priority": 3,
  "status": "completed",
  "created_by": "polybot",
  "created_at": "2026-03-04T05:51:45.978641+00:00",
  "updated_at": "2026-03-04T05:52:16.497994+00:00",
  "claimed_at": "2026-03-04T05:52:14.899711+00:00",
  "completed_at": "2026-03-04T05:52:16.497975+00:00",
  "retries": 0,
  "result": {
    "summary": "Research: Spurs vs. 76ers\n\nWeb Results (0):\n  No web results found.",
    "web_results": [],
    "news_results": [],
    "query": "Spurs vs. 76ers",
    "sources_count": 0
  },
  "error": null
}