{
  "id": "7535ea16",
  "title": "Polymarket research: Will Alireza Arafi be the next Supreme Leader of Iran?",
  "assigned_to": "natalia",
  "task_type": "research",
  "params": {
    "query": "Will Alireza Arafi be the next Supreme Leader of Iran?",
    "count": 5,
    "context": "polymarket_prediction",
    "requester": "polybot"
  },
  "priority": 3,
  "status": "completed",
  "created_by": "polybot",
  "created_at": "2026-03-03T01:57:01.089241+00:00",
  "updated_at": "2026-03-03T01:57:44.841604+00:00",
  "claimed_at": "2026-03-03T01:57:43.174723+00:00",
  "completed_at": "2026-03-03T01:57:44.841587+00:00",
  "retries": 0,
  "result": {
    "summary": "Research: Will Alireza Arafi be the next Supreme Leader of Iran?\n\nWeb Results (0):\n  No web results found.",
    "web_results": [],
    "news_results": [],
    "query": "Will Alireza Arafi be the next Supreme Leader of Iran?",
    "sources_count": 0
  },
  "error": null
}