{
  "id": "9796b9cb",
  "title": "Polymarket research: Raptors vs. Timberwolves",
  "assigned_to": "natalia",
  "task_type": "research",
  "params": {
    "query": "Raptors vs. Timberwolves",
    "count": 5,
    "context": "polymarket_prediction",
    "requester": "polybot"
  },
  "priority": 3,
  "status": "completed",
  "created_by": "polybot",
  "created_at": "2026-03-06T02:32:12.892385+00:00",
  "updated_at": "2026-03-06T02:32:25.514105+00:00",
  "claimed_at": "2026-03-06T02:32:23.888944+00:00",
  "completed_at": "2026-03-06T02:32:25.514087+00:00",
  "retries": 0,
  "result": {
    "summary": "Research: Raptors vs. Timberwolves\n\nWeb Results (0):\n  No web results found.",
    "web_results": [],
    "news_results": [],
    "query": "Raptors vs. Timberwolves",
    "sources_count": 0
  },
  "error": null
}