{
  "id": "9d3d3d01",
  "title": "Polymarket research: Spread: Timberwolves (-14.5)",
  "assigned_to": "natalia",
  "task_type": "research",
  "params": {
    "query": "Spread: Timberwolves (-14.5)",
    "count": 5,
    "context": "polymarket_prediction",
    "requester": "polybot"
  },
  "priority": 3,
  "status": "completed",
  "created_by": "polybot",
  "created_at": "2026-03-04T06:00:57.286159+00:00",
  "updated_at": "2026-03-04T06:01:38.766181+00:00",
  "claimed_at": "2026-03-04T06:01:37.713916+00:00",
  "completed_at": "2026-03-04T06:01:38.766164+00:00",
  "retries": 0,
  "result": {
    "summary": "Research: Spread: Timberwolves (-14.5)\n\nWeb Results (0):\n  No web results found.",
    "web_results": [],
    "news_results": [],
    "query": "Spread: Timberwolves (-14.5)",
    "sources_count": 0
  },
  "error": null
}