{
  "id": "af3e3f24",
  "title": "Polymarket research: Will the next Prime Minister of Hungary be Kl\u00e1ra Dobrev?",
  "assigned_to": "natalia",
  "task_type": "research",
  "params": {
    "query": "Will the next Prime Minister of Hungary be Kl\u00e1ra Dobrev?",
    "count": 5,
    "context": "polymarket_prediction",
    "requester": "polybot"
  },
  "priority": 3,
  "status": "completed",
  "created_by": "polybot",
  "created_at": "2026-03-06T22:52:33.979814+00:00",
  "updated_at": "2026-03-06T22:53:45.890849+00:00",
  "claimed_at": "2026-03-06T22:53:44.246280+00:00",
  "completed_at": "2026-03-06T22:53:45.890837+00:00",
  "retries": 0,
  "result": {
    "summary": "Research: Will the next Prime Minister of Hungary be Kl\u00e1ra Dobrev?\n\nWeb Results (0):\n  No web results found.",
    "web_results": [],
    "news_results": [],
    "query": "Will the next Prime Minister of Hungary be Kl\u00e1ra Dobrev?",
    "sources_count": 0
  },
  "error": null
}