{
  "id": "b10e88f0",
  "title": "Polymarket research: Will Crystal Palace FC win on 2026-03-05?",
  "assigned_to": "natalia",
  "task_type": "research",
  "params": {
    "query": "Will Crystal Palace FC win on 2026-03-05?",
    "count": 5,
    "context": "polymarket_prediction",
    "requester": "polybot"
  },
  "priority": 3,
  "status": "completed",
  "created_by": "polybot",
  "created_at": "2026-03-05T19:57:39.706772+00:00",
  "updated_at": "2026-03-05T19:57:53.437507+00:00",
  "claimed_at": "2026-03-05T19:57:51.770961+00:00",
  "completed_at": "2026-03-05T19:57:53.437475+00:00",
  "retries": 0,
  "result": {
    "summary": "Research: Will Crystal Palace FC win on 2026-03-05?\n\nWeb Results (0):\n  No web results found.",
    "web_results": [],
    "news_results": [],
    "query": "Will Crystal Palace FC win on 2026-03-05?",
    "sources_count": 0
  },
  "error": null
}