{
  "id": "b2687d56",
  "title": "Polymarket research: Bitcoin Up or Down - March 6, 11AM ET",
  "assigned_to": "natalia",
  "task_type": "research",
  "params": {
    "query": "Bitcoin Up or Down - March 6, 11AM ET",
    "count": 5,
    "context": "polymarket_prediction",
    "requester": "polybot"
  },
  "priority": 3,
  "status": "completed",
  "created_by": "polybot",
  "created_at": "2026-03-06T17:30:26.377712+00:00",
  "updated_at": "2026-03-06T17:30:53.481445+00:00",
  "claimed_at": "2026-03-06T17:30:51.841661+00:00",
  "completed_at": "2026-03-06T17:30:53.481429+00:00",
  "retries": 0,
  "result": {
    "summary": "Research: Bitcoin Up or Down - March 6, 11AM ET\n\nWeb Results (0):\n  No web results found.",
    "web_results": [],
    "news_results": [],
    "query": "Bitcoin Up or Down - March 6, 11AM ET",
    "sources_count": 0
  },
  "error": null
}