{
  "id": "dbf80595",
  "title": "Polymarket research: Miami Open: Alexandra Eala vs Laura Siegemund",
  "assigned_to": "natalia",
  "task_type": "research",
  "params": {
    "query": "Miami Open: Alexandra Eala vs Laura Siegemund",
    "count": 5,
    "context": "polymarket_prediction",
    "requester": "polybot"
  },
  "priority": 3,
  "status": "completed",
  "created_by": "polybot",
  "created_at": "2026-03-19T19:10:28.471337+00:00",
  "updated_at": "2026-03-19T19:11:58.091432+00:00",
  "claimed_at": "2026-03-19T19:11:56.404134+00:00",
  "completed_at": "2026-03-19T19:11:58.091416+00:00",
  "retries": 0,
  "result": {
    "summary": "Research: Miami Open: Alexandra Eala vs Laura Siegemund\n\nWeb Results (0):\n  No web results found.",
    "web_results": [],
    "news_results": [],
    "query": "Miami Open: Alexandra Eala vs Laura Siegemund",
    "sources_count": 0
  },
  "error": null
}