{
  "id": "efd5dc35",
  "title": "Polymarket research: Will Bitcoin reach $110,000 in March?",
  "assigned_to": "natalia",
  "task_type": "research",
  "params": {
    "query": "Will Bitcoin reach $110,000 in March?",
    "count": 5,
    "context": "polymarket_prediction",
    "requester": "polybot"
  },
  "priority": 3,
  "status": "completed",
  "created_by": "polybot",
  "created_at": "2026-03-05T07:16:59.347455+00:00",
  "updated_at": "2026-03-05T07:18:00.446938+00:00",
  "claimed_at": "2026-03-05T07:17:58.851114+00:00",
  "completed_at": "2026-03-05T07:18:00.446919+00:00",
  "retries": 0,
  "result": {
    "summary": "Research: Will Bitcoin reach $110,000 in March?\n\nWeb Results (0):\n  No web results found.",
    "web_results": [],
    "news_results": [],
    "query": "Will Bitcoin reach $110,000 in March?",
    "sources_count": 0
  },
  "error": null
}