{
  "id": "f79cd470",
  "title": "Polymarket research: Trail Blazers vs. Grizzlies: O/U 235.5",
  "assigned_to": "natalia",
  "task_type": "research",
  "params": {
    "query": "Trail Blazers vs. Grizzlies: O/U 235.5",
    "count": 5,
    "context": "polymarket_prediction",
    "requester": "polybot"
  },
  "priority": 3,
  "status": "completed",
  "created_by": "polybot",
  "created_at": "2026-03-05T03:23:54.897965+00:00",
  "updated_at": "2026-03-05T03:24:11.119178+00:00",
  "claimed_at": "2026-03-05T03:24:10.043984+00:00",
  "completed_at": "2026-03-05T03:24:11.119161+00:00",
  "retries": 0,
  "result": {
    "summary": "Research: Trail Blazers vs. Grizzlies: O/U 235.5\n\nWeb Results (0):\n  No web results found.",
    "web_results": [],
    "news_results": [],
    "query": "Trail Blazers vs. Grizzlies: O/U 235.5",
    "sources_count": 0
  },
  "error": null
}