{
  "id": "f9d06619",
  "title": "Polymarket research: Spurs vs. Nets",
  "assigned_to": "natalia",
  "task_type": "research",
  "params": {
    "query": "Spurs vs. Nets",
    "count": 5,
    "context": "polymarket_prediction",
    "requester": "polybot"
  },
  "priority": 3,
  "status": "completed",
  "created_by": "polybot",
  "created_at": "2026-02-27T03:43:14.986768+00:00",
  "updated_at": "2026-02-27T03:43:26.568664+00:00",
  "claimed_at": "2026-02-27T03:43:24.948621+00:00",
  "completed_at": "2026-02-27T03:43:26.568648+00:00",
  "retries": 0,
  "result": {
    "summary": "Research: Spurs vs. Nets\n\nWeb Results (0):\n  No web results found.",
    "web_results": [],
    "news_results": [],
    "query": "Spurs vs. Nets",
    "sources_count": 0
  },
  "error": null
}