{
  "id": "fb5da746",
  "title": "MCP server new tools integrations 2026",
  "assigned_to": "natalia",
  "task_type": "intelligence",
  "params": {
    "query": "MCP server new tools integrations 2026",
    "category": "tech_upgrades"
  },
  "priority": 8,
  "status": "completed",
  "created_by": "natalia-auto",
  "created_at": "2026-02-28T14:38:22.217327+00:00",
  "updated_at": "2026-02-28T14:38:23.868937+00:00",
  "claimed_at": "2026-02-28T14:38:22.224093+00:00",
  "completed_at": "2026-02-28T14:38:23.868919+00:00",
  "retries": 0,
  "result": {
    "summary": "Intelligence: MCP server new tools integrations 2026\n\nFindings (0):\n",
    "findings": [],
    "query": "MCP server new tools integrations 2026",
    "sources_count": 0,
    "findings_count": 0,
    "market_movers": 0,
    "opportunities": 0
  },
  "error": null
}